[
     {
      "medicine": "DOMCET",
      "alternatives": ["Domperidone", "Ondansetron"]
    },
     {
      "medicine": "DOMPAR",
      "alternatives": ["Domperidone", "Metoclopramide"]
    },
     {
      "medicine": "ACI FREE (LEMON)",
      "alternatives": ["Aluminum Hydroxide", "Magnesium Hydroxide"]
    },
     {
      "medicine": "ACI FREE (PUDINA)",
      "alternatives": ["Aluminum Hydroxide", "Simethicone"]
    },
     {
      "medicine": "ACI FREE (REGULAR)",
      "alternatives": ["Calcium Carbonate", "Magnesium Hydroxide"]
    },
     {
      "medicine": "ACI FREE (ZEERA)",
      "alternatives": ["Sodium Bicarbonate", "Aluminum Hydroxide"]
    },
     {
      "medicine": "ACIGENE GEL 170ML MINT",
      "alternatives": ["Magaldrate", "Simethicone"]
    },
     {
      "medicine": "DIGUSIL MPS (MINT)",
      "alternatives": ["Aluminum Hydroxide", "Magnesium Hydroxide"]
    },
     {
      "medicine": "OXECAINE 170ML",
      "alternatives": ["Oxetacaine", "Antacid (combination)"]
    },
     {
      "medicine": "ALERGIN",
      "alternatives": ["Cetirizine", "Loratadine"]
    },
     {
      "medicine": "ALERGIN - L",
      "alternatives": ["Levocetirizine", "Fexofenadine"]
    },
     {
      "medicine": "BILACIP TABS",
      "alternatives": ["Bilastine", "Loratadine"]
    },
     {
      "medicine": "BILACIP-M",
      "alternatives": ["Bilastine", "Montelukast"]
    },
     {
      "medicine": "CETCIP",
      "alternatives": ["Cetirizine", "Levocetirizine"]
    },
     {
      "medicine": "CETCIP - L",
      "alternatives": ["Levocetirizine", "Desloratadine"]
    },
     {
      "medicine": "CETCIP 30 ML",
      "alternatives": ["Cetirizine Syrup", "Levocetirizine Syrup"]
    },
     {
      "medicine": "EMIN",
      "alternatives": ["Promethazine", "Meclizine"]
    },
     {
      "medicine": "FEXIGRA 120 TABS",
      "alternatives": ["Fexofenadine", "Loratadine"]
    },
     {
      "medicine": "FEXIGRA 180 TABS",
      "alternatives": ["Fexofenadine", "Desloratadine"]
    },
     {
      "medicine": "FEXIGRA-M TABS",
      "alternatives": ["Fexofenadine", "Montelukast"]
    },
     {
      "medicine": "LORATIN",
      "alternatives": ["Loratadine", "Cetirizine"]
    },
     {
      "medicine": "MONTECIP BL TABS",
      "alternatives": ["Montelukast", "Levocetirizine"]
    },
     {
      "medicine": "MONTECIP LC JUNIOR SYRUP",
      "alternatives": ["Montelukast Syrup", "Levocetirizine Syrup"]
    },
     {
      "medicine": "MONTECIP LC TABS",
      "alternatives": ["Montelukast", "Levocetirizine"]
    },
     {
      "medicine": "MONTECIP-FX TABS",
      "alternatives": ["Montelukast", "Fexofenadine"]
    },
     {
      "medicine": "NEW OKACET",
      "alternatives": ["Cetirizine", "Levocetirizine"]
    },
     {
      "medicine": "OKACET 10 MG",
      "alternatives": ["Cetirizine", "Desloratadine"]
    },
     {
      "medicine": "OKACET - L",
      "alternatives": ["Levocetirizine", "Fexofenadine"]
    },
     {
      "medicine": "OKACET - L 30ML",
      "alternatives": ["Levocetirizine Syrup", "Cetirizine Syrup"]
    },
     {
      "medicine": "OKACET SYRUP",
      "alternatives": ["Cetirizine Syrup", "Loratadine Syrup"]
    },
     {
      "medicine": "VERTIRON",
      "alternatives": ["Betahistine", "Meclizine"]
    },
     {
      "medicine": "DERICIP",
      "alternatives": ["Theophylline", "Aminophylline"]
    },
     {
      "medicine": "DERICIP 150 RETARD",
      "alternatives": ["Theophylline", "Aminophylline"]
    },
     {
      "medicine": "DERICIP 300 RETARD",
      "alternatives": ["Theophylline", "Aminophylline"]
    },
     {
      "medicine": "DOXOCIP",
      "alternatives": ["Doxycycline", "Tetracycline"]
    },
     {
      "medicine": "AZICIP 100 ORAL SUSPN",
      "alternatives": ["Azithromycin", "Erythromycin"]
    },
     {
      "medicine": "AZICIP 200 ORAL SUSPN",
      "alternatives": ["Azithromycin", "Clarithromycin"]
    },
     {
      "medicine": "AZICIP 250",
      "alternatives": ["Azithromycin", "Erythromycin"]
    },
     {
      "medicine": "AZICIP 500",
      "alternatives": ["Azithromycin", "Clarithromycin"]
    },
     {
      "medicine": "AZIPRO 250",
      "alternatives": ["Azithromycin", "Roxithromycin"]
    },
     {
      "medicine": "AZIPRO 500",
      "alternatives": ["Azithromycin", "Clarithromycin"]
    },
     {
      "medicine": "AZOMYCIN 100",
      "alternatives": ["Azithromycin", "Erythromycin"]
    },
     {
      "medicine": "AZOMYCIN 200",
      "alternatives": ["Azithromycin", "Clarithromycin"]
    },
     {
      "medicine": "AZOMYCIN 250 TABS",
      "alternatives": ["Azithromycin", "Erythromycin"]
    },
     {
      "medicine": "AZOMYCIN 500",
      "alternatives": ["Azithromycin", "Clarithromycin"]
    },
     {
      "medicine": "CEFASYN 250 4'S",
      "alternatives": ["Cefuroxime", "Cefixime"]
    },
     {
      "medicine": "CEFASYN 250 10'S",
      "alternatives": ["Cefuroxime", "Cefixime"]
    },
     {
      "medicine": "CEFASYN 500 4'S",
      "alternatives": ["Cefuroxime", "Cefixime"]
    },
     {
      "medicine": "CEFASYN 500 10'S",
      "alternatives": ["Cefuroxime", "Cefixime"]
    },
     {
      "medicine": "CEFIX 100",
      "alternatives": ["Cefixime", "Cefuroxime"]
    },
     {
      "medicine": "CEFIX 200",
      "alternatives": ["Cefixime", "Cefpodoxime"]
    },
     {
      "medicine": "CEFIX 200 (O)",
      "alternatives": ["Cefixime", "Cefpodoxime"]
    },
     {
      "medicine": "CEFIX DS 30ML",
      "alternatives": ["Cefixime", "Cefpodoxime"]
    },
     {
      "medicine": "CEFIX DS STRAWBERRY",
      "alternatives": ["Cefixime", "Cefpodoxime"]
    },
     {
      "medicine": "CEFIX - O",
      "alternatives": ["Cefixime", "Cefuroxime"]
    },
     {
      "medicine": "CEFRAX 100",
      "alternatives": ["Cefixime", "Cefpodoxime"]
    },
     {
      "medicine": "CEFRAX 200",
      "alternatives": ["Cefixime", "Cefuroxime"]
    },
     {
      "medicine": "CEFRAX CV",
      "alternatives": ["Cefixime", "Clavulanic Acid"]
    },
     {
      "medicine": "CEFRAX DS 30 ML",
      "alternatives": ["Cefixime", "Cefuroxime"]
    },
     {
      "medicine": "CEFRAX O 10'S",
      "alternatives": ["Cefixime", "Cefpodoxime"]
    },
     {
      "medicine": "CEFTAZ-1000MG",
      "alternatives": ["Ceftazidime", "Ceftriaxone"]
    },
     {
      "medicine": "CEPHADEX 125DT",
      "alternatives": ["Cefalexin", "Cefadroxil"]
    },
     {
      "medicine": "CEPHADEX 250",
      "alternatives": ["Cefalexin", "Cefadroxil"]
    },
     {
      "medicine": "CEPHADEX 250 DT",
      "alternatives": ["Cefalexin", "Cefadroxil"]
    },
     {
      "medicine": "CEPHADEX 500",
      "alternatives": ["Cefalexin", "Cefadroxil"]
    },
     {
      "medicine": "CEPHADEX DS",
      "alternatives": ["Cefalexin", "Cefadroxil"]
    },
     {
      "medicine": "CIPDOXIVID - LB CAPS",
      "alternatives": ["Ciprofloxacin", "Levofloxacin"]
    },
     {
      "medicine": "CIPLOX IV (POUCH) 100 ML",
      "alternatives": ["Ciprofloxacin", "Levofloxacin"]
    },
     {
      "medicine": "CIPMOX 250 DT",
      "alternatives": ["Amoxicillin", "Ampicillin"]
    },
     {
      "medicine": "CIPMOX 500 YELLOW 15'S",
      "alternatives": ["Amoxicillin", "Ampicillin"]
    },
     {
      "medicine": "CIPMOX CV",
      "alternatives": ["Amoxicillin", "Clavulanic Acid"]
    },
     {
      "medicine": "CIPMOX CV 625 10'S",
      "alternatives": ["Amoxicillin", "Clavulanic Acid"]
    },
     {
      "medicine": "ETOZOX- T TABS",
      "alternatives": ["Etoricoxib", "Diclofenac"]
    },
     {
      "medicine": "L QUIN 250",
      "alternatives": ["Levofloxacin", "Ofloxacin"]
    },
     {
      "medicine": "L QUIN 500",
      "alternatives": ["Levofloxacin", "Ofloxacin"]
    },
     {
      "medicine": "L QUIN 750",
      "alternatives": ["Levofloxacin", "Moxifloxacin"]
    },
     {
      "medicine": "LEVOQUIN 250",
      "alternatives": ["Levofloxacin", "Ofloxacin"]
    },
     {
      "medicine": "LEVOQUIN 500",
      "alternatives": ["Levofloxacin", "Moxifloxacin"]
    },
     {
      "medicine": "MEGACLOX",
      "alternatives": ["Amoxicillin", "Cloxacillin"]
    },
     {
      "medicine": "MEGACLOX DT (NEW)",
      "alternatives": ["Amoxicillin", "Cloxacillin"]
    },
     {
      "medicine": "MUPICIP 5GM",
      "alternatives": ["Mupirocin", "Neomycin"]
    },
     {
      "medicine": "MUPICIP 10GM",
      "alternatives": ["Mupirocin", "Neomycin"]
    },
     {
      "medicine": "MUPICIP 15GM",
      "alternatives": ["Mupirocin", "Neomycin"]
    },
     {
      "medicine": "NOVACLOX-LB",
      "alternatives": ["Amoxicillin", "Clavulanic Acid"]
    },
     {
      "medicine": "NOVACLAV 625 6'S",
      "alternatives": ["Amoxicillin", "Clavulanic Acid"]
    },
     {
      "medicine": "NOVACLAV 625 10'S",
      "alternatives": ["Amoxicillin", "Clavulanic Acid"]
    },
     {
      "medicine": "NOVACLAV DRY",
      "alternatives": ["Amoxicillin", "Clavulanic Acid"]
    },
     {
      "medicine": "NOVACLOX NF",
      "alternatives": ["Amoxicillin", "Cloxacillin"]
    },
     {
      "medicine": "OLOX 200",
      "alternatives": ["Ofloxacin", "Levofloxacin"]
    },
     {
      "medicine": "OLOX OZ",
      "alternatives": ["Ofloxacin", "Ornidazole"]
    },
     {
      "medicine": "OMNICLAV 375",
      "alternatives": ["Amoxicillin", "Clavulanic Acid"]
    },
     {
    "medicine": "OMNICLAV 625",
    "alternatives": ["Amoxicillin", "Clavulanic Acid"]
    },
     {
    "medicine": "OMNICLAV 625",
    "alternatives": ["Amoxicillin", "Clavulanic Acid"]
  },
   {
    "medicine": "OMNICLAV DS 30ML",
    "alternatives": ["Amoxicillin", "Clavulanic Acid"]
  },
   {
    "medicine": "PODOCIP 200 10'S",
    "alternatives": ["Cefpodoxime", "Cefixime"]
  },
   {
    "medicine": "PODOCIP CV",
    "alternatives": ["Cefpodoxime", "Clavulanic Acid"]
  },
   {
    "medicine": "POWERGYL OZ",
    "alternatives": ["Ornidazole", "Ofloxacin"]
  },
   {
    "medicine": "ROXEE 150",
    "alternatives": ["Roxithromycin", "Azithromycin"]
  },
   {
    "medicine": "TARIFLOX 200",
    "alternatives": ["Ofloxacin", "Levofloxacin"]
  },
   {
    "medicine": "TARIFLOX OZ",
    "alternatives": ["Ofloxacin", "Ornidazole"]
  },
   {
    "medicine": "ZOCLAR 250",
    "alternatives": ["Clarithromycin", "Azithromycin"]
  },
   {
    "medicine": "ZOCLAR 500",
    "alternatives": ["Clarithromycin", "Azithromycin"]
  },
   {
    "medicine": "ALERGIN COLD AND FLU NF",
    "alternatives": ["Paracetamol", "Phenylephrine"]
  },
   {
    "medicine": "ALERGIN COLD TOTAL",
    "alternatives": ["Paracetamol", "Chlorpheniramine"]
  },
   {
    "medicine": "CHESTON COLD",
    "alternatives": ["Paracetamol", "Phenylephrine"]
  },
   {
    "medicine": "CHESTON COLD (AMBER)",
    "alternatives": ["Paracetamol", "Chlorpheniramine"]
  },
   {
    "medicine": "CHESTON COLD & FLU NF",
    "alternatives": ["Paracetamol", "Phenylephrine"]
  },
   {
    "medicine": "CHESTON COLD DS 60 ML",
    "alternatives": ["Paracetamol Syrup", "Phenylephrine Syrup"]
  },
   {
    "medicine": "CHESTON COLD NEW (SILVER)",
    "alternatives": ["Paracetamol", "Chlorpheniramine"]
  },
   {
    "medicine": "CHESTON COLD TOTAL",
    "alternatives": ["Paracetamol", "Phenylephrine"]
  },
   {
    "medicine": "CHESTON COLD 20'S",
    "alternatives": ["Paracetamol", "Chlorpheniramine"]
  },
   {
    "medicine": "CHESTON COLD 60ML",
    "alternatives": ["Paracetamol Syrup", "Chlorpheniramine Syrup"]
  },
   {
    "medicine": "EASI BREATHE SOFTGEL",
    "alternatives": ["Guaifenesin", "Phenylephrine"]
  },
   {
    "medicine": "NICIP COLD & FLU NF",
    "alternatives": ["Paracetamol", "Chlorpheniramine"]
  },
   {
    "medicine": "NIMUPAIN COLD & FLU NF",
    "alternatives": ["Nimesulide", "Phenylephrine"]
  },
   {
    "medicine": "NOCOLD",
    "alternatives": ["Paracetamol", "Chlorpheniramine"]
  },
   {
    "medicine": "NOCOLD PLUS",
    "alternatives": ["Paracetamol", "Phenylephrine"]
  },
   {
    "medicine": "NOCOLD 60ML",
    "alternatives": ["Paracetamol Syrup", "Chlorpheniramine Syrup"]
  },
   {
    "medicine": "OKACET COLD",
    "alternatives": ["Paracetamol", "Chlorpheniramine"]
  },
   {
    "medicine": "OKACET COLD TOTAL",
    "alternatives": ["Paracetamol", "Phenylephrine"]
  },
   {
    "medicine": "ACARCIP-25 TABS",
    "alternatives": ["Acarbose", "Metformin"]
  },
   {
    "medicine": "ACARCIP-50 TABS",
    "alternatives": ["Acarbose", "Metformin"]
  },
   {
    "medicine": "CIPDAPLA 10",
    "alternatives": ["Dapagliflozin", "Metformin"]
  },
   {
    "medicine": "CIPDAPLA 5",
    "alternatives": ["Dapagliflozin", "Metformin"]
  },
   {
    "medicine": "CIPDAPLA-M 10/1000 TABS",
    "alternatives": ["Dapagliflozin", "Metformin"]
  },
   {
    "medicine": "CIPDAPLA-M 10/500 TABS",
    "alternatives": ["Dapagliflozin", "Metformin"]
  },
   {
    "medicine": "CIPVILDIN 50 TABS",
    "alternatives": ["Vildagliptin", "Metformin"]
  },
   {
    "medicine": "CIPVILDIN-M TABS 50/1000",
    "alternatives": ["Vildagliptin", "Metformin"]
  },
   {
    "medicine": "CIPVILDIN-M TABS 50/500",
    "alternatives": ["Vildagliptin", "Metformin"]
  },
   {
    "medicine": "ETHAMCIP 250",
    "alternatives": ["Ethambutol", "Isoniazid"]
  },
   {
    "medicine": "ETHAMCIP 500",
    "alternatives": ["Ethambutol", "Isoniazid"]
  },
   {
    "medicine": "GLIMDA 1",
    "alternatives": ["Glimepiride", "Metformin"]
  },
   {
    "medicine": "GLIMDA 2",
    "alternatives": ["Glimepiride", "Metformin"]
  },
   {
    "medicine": "GLIMDA 3 TAB",
    "alternatives": ["Glimepiride", "Metformin"]
  },
   {
    "medicine": "GLIMDA-MV 1",
    "alternatives": ["Glimepiride", "Metformin"]
  },
   {
    "medicine": "GLIMDA-MV 2",
    "alternatives": ["Glimepiride", "Metformin"]
  },
   {
    "medicine": "GLINIL",
    "alternatives": ["Glibenclamide", "Metformin"]
  },
   {
    "medicine": "GLINIL M",
    "alternatives": ["Glibenclamide", "Metformin"]
  },
   {
    "medicine": "GLYGARD",
    "alternatives": ["Gliclazide", "Metformin"]
  },
   {
    "medicine": "GLYGARD M",
    "alternatives": ["Gliclazide", "Metformin"]
  },
   {
    "medicine": "METFOR 500",
    "alternatives": ["Metformin", "Glimepiride"]
  },
   {
    "medicine": "OKAMET 500",
    "alternatives": ["Metformin", "Glimepiride"]
  },
   {
    "medicine": "OKAMET 500 SR",
    "alternatives": ["Metformin", "Glimepiride"]
  },
   {
    "medicine": "OKAMET GM 1002 TABS",
    "alternatives": ["Metformin", "Glimepiride"]
  },
   {
    "medicine": "OKAMET GM 501 TABS",
    "alternatives": ["Metformin", "Glimepiride"]
  },
   {
    "medicine": "OKAMET GM 502 TABS",
    "alternatives": ["Metformin", "Glimepiride"]
  },
   {
    "medicine": "OKAMET GMP 1 TABS",
    "alternatives": ["Metformin", "Pioglitazone"]
  },
   {
    "medicine": "OKAMET GMP 2 TABS",
    "alternatives": ["Metformin", "Pioglitazone"]
  },
   {
    "medicine": "TENEPLA",
    "alternatives": ["Teneligliptin", "Metformin"]
  },
   {
    "medicine": "TENEPLA M 500",
    "alternatives": ["Teneligliptin", "Metformin"]
  },
   {
    "medicine": "TENEPLA M 1000",
    "alternatives": ["Teneligliptin", "Metformin"]
  },
   {
    "medicine": "TENEPLA M 1000 TABS",
    "alternatives": ["Teneligliptin", "Metformin"]
  },
   {
    "medicine": "VOGLICIP 0.2",
    "alternatives": ["Voglibose", "Acarbose"]
  },
   {
    "medicine": "VOGLICIP M 0.2 TABS",
    "alternatives": ["Voglibose", "Metformin"]
  },
   {
    "medicine": "VOGLICIP 0.3",
    "alternatives": ["Voglibose", "Acarbose"]
  },
   {
    "medicine": "OFLOX OZ NF 30 ML",
    "alternatives": ["Ofloxacin", "Ornidazole"]
  }
]